bin/c5.0
bin/report
c50/__init__.py
c50/c50_base.py
c50/c50_rules.py
c50/c50_tree.py
c50/estimator_loader.py
c50/names_file_builder.py
c50/parsers/__init__.py
c50/parsers/base_parser.py
c50/parsers/common_parsers.py
c50/parsers/parser_types.py
c50/parsers/rules_parser.py
c50/parsers/tree_parsers/__init__.py
c50/parsers/tree_parsers/tree_parser.py
c50/templates/rule_estimator_template.py.jinja
c50/templates/tree_estimator_template.py.jinja
c50/templates/weights.costs.jinja
c50_wrapper-0.1.0.dist-info/METADATA
c50_wrapper-0.1.0.dist-info/WHEEL
c50_wrapper-0.1.0.dist-info/top_level.txt
c50_wrapper-0.1.0.dist-info/RECORD
