Metadata-Version: 2.4
Name: c50-wrapper
Version: 0.1.0
Summary: A python wrapper fot the C5.0 algorithm that works on linux applications; 
Author-email: SERVICE PREVENTION <anti-fraud@bemobi.com>
Keywords: Decision Tree,C5.0,Machine Learning
Requires-Python: >=3.8
Requires-Dist: pyparsing>=3.1
Requires-Dist: jinja2>=3.1
Requires-Dist: pandas>=2.0
Requires-Dist: pyyaml>=6.0
Requires-Dist: numpy>=1.22
Requires-Dist: scipy>=1.11
Provides-Extra: dev
Requires-Dist: pylint; extra == "dev"
Requires-Dist: black; extra == "dev"
Requires-Dist: mypy; extra == "dev"
Requires-Dist: flake8; extra == "dev"
Requires-Dist: pyflakes; extra == "dev"
Requires-Dist: pycodestyle; extra == "dev"
Requires-Dist: pydocstyle; extra == "dev"
Requires-Dist: pre-commit; extra == "dev"
Requires-Dist: sphinx; extra == "dev"
Requires-Dist: twine; extra == "dev"
Requires-Dist: matplotlib; extra == "dev"
Requires-Dist: jupyterlab; extra == "dev"
